mxp/__init__.py
mxp/tests.py
mxp-0.1.3.dist-info/LICENSE
mxp-0.1.3.dist-info/METADATA
mxp-0.1.3.dist-info/WHEEL
mxp-0.1.3.dist-info/top_level.txt
mxp-0.1.3.dist-info/RECORD
