Metadata-Version: 2.1
Name: mxp
Version: 0.1.3
Summary: qPCR fileformat reader
Home-page: http://www.imt.uni-marburg.de
Author: Florian Finkernagel
Author-email: finkernagel@imt.uni-marburg.de
License: UNKNOWN
Keywords: qPCR,MXP
Platform: UNKNOWN
Classifier: Programming Language :: Python
Classifier: Development Status :: 5 - Production/Stable
Classifier: Environment :: Other Environment
Classifier: Intended Audience :: Developers
Classifier: License :: OSI Approved :: GNU Library or Lesser General Public License (LGPL)
Classifier: Operating System :: OS Independent
Classifier: Topic :: Software Development :: Libraries :: Python Modules
Requires-Dist: olefile
Requires-Dist: pandas
